pdfformulas/__init__.py
pdfformulas/pdfformulas.py
pdfformulas-0.0.6.dist-info/DESCRIPTION.rst
pdfformulas-0.0.6.dist-info/METADATA
pdfformulas-0.0.6.dist-info/RECORD
pdfformulas-0.0.6.dist-info/WHEEL
pdfformulas-0.0.6.dist-info/entry_points.txt
pdfformulas-0.0.6.dist-info/metadata.json
pdfformulas-0.0.6.dist-info/top_level.txt
