Metadata-Version: 2.0
Name: pdfformulas
Version: 0.0.6
Summary: pdfformulas dumps the formulas of a PDF as PNG files in the ``formulas`` subfolder.
Home-page: https://github.com/rpuntaie/pdfformulas
Author: Roland Puntaier
Author-email: roland.puntaier@gmail.com
License: MIT
Keywords: PDF, Formula
Platform: UNKNOWN
Classifier: Development Status :: 3 - Alpha
Classifier: Intended Audience :: Education
Classifier: License :: OSI Approved :: MIT License
Classifier: Operating System :: POSIX :: Linux
Classifier: Programming Language :: Python
Classifier: Programming Language :: Python :: 2.7
Requires-Dist: PdfMiner (>=20140328)
Requires-Dist: Pillow (>=3.1.0)
